{"trial_id": "0021", "hyperparameters": {"space": [{"class_name": "Int", "config": {"name": "conv_layers", "default": null, "conditions": [], "min_value": 1, "max_value": 3, "step": 1, "sampling": "linear"}}, {"class_name": "Int", "config": {"name": "filters_0", "default": null, "conditions": [], "min_value": 16, "max_value": 128, "step": 16, "sampling": "linear"}}, {"class_name": "Choice", "config": {"name": "kernel_size_0", "default": 3, "conditions": [], "values": [3, 5], "ordered": true}}, {"class_name": "Int", "config": {"name": "dense_units", "default": null, "conditions": [], "min_value": 64, "max_value": 256, "step": 32, "sampling": "linear"}}, {"class_name": "Choice", "config": {"name": "loss_type", "default": "focal", "conditions": [], "values": ["focal", "categorical_crossentropy"], "ordered": false}}, {"class_name": "Choice", "config": {"name": "learning_rate", "default": 0.001, "conditions": [], "values": [0.001, 0.0001, 1e-05], "ordered": true}}, {"class_name": "Int", "config": {"name": "filters_1", "default": null, "conditions": [], "min_value": 16, "max_value": 128, "step": 16, "sampling": "linear"}}, {"class_name": "Choice", "config": {"name": "kernel_size_1", "default": 3, "conditions": [], "values": [3, 5], "ordered": true}}, {"class_name": "Int", "config": {"name": "filters_2", "default": null, "conditions": [], "min_value": 16, "max_value": 128, "step": 16, "sampling": "linear"}}, {"class_name": "Choice", "config": {"name": "kernel_size_2", "default": 3, "conditions": [], "values": [3, 5], "ordered": true}}], "values": {"conv_layers": 3, "filters_0": 112, "kernel_size_0": 5, "dense_units": 160, "loss_type": "categorical_crossentropy", "learning_rate": 1e-05, "filters_1": 48, "kernel_size_1": 5, "filters_2": 64, "kernel_size_2": 3, "tuner/epochs": 2, "tuner/initial_epoch": 0, "tuner/bracket": 3, "tuner/round": 0}}, "metrics": {"metrics": {"accuracy": {"direction": "max", "observations": [{"value": [0.5265354514122009], "step": 1}]}, "auc": {"direction": "max", "observations": [{"value": [0.6934345364570618], "step": 1}]}, "f1_score": {"direction": "min", "observations": [{"value": [0.015229970216751099], "step": 1}]}, "loss": {"direction": "min", "observations": [{"value": [5.966209888458252], "step": 1}]}, "precision": {"direction": "max", "observations": [{"value": [0.5952380895614624], "step": 1}]}, "recall": {"direction": "max", "observations": [{"value": [0.014907573349773884], "step": 1}]}, "val_accuracy": {"direction": "max", "observations": [{"value": [0.5205724239349365], "step": 1}]}, "val_auc": {"direction": "max", "observations": [{"value": [0.7781609296798706], "step": 1}]}, "val_f1_score": {"direction": "max", "observations": [{"value": [0.02801361307501793], "step": 1}]}, "val_loss": {"direction": "min", "observations": [{"value": [1.8483648300170898], "step": 1}]}, "val_precision": {"direction": "max", "observations": [{"value": [0.8333333134651184], "step": 1}]}, "val_recall": {"direction": "max", "observations": [{"value": [0.026833631098270416], "step": 1}]}}}, "score": 0.02801361307501793, "best_step": 1, "status": "COMPLETED", "message": null}